pamsbel/__init__.py
pamsbel/main.py
pamsbel-0.0.2.dist-info/LICENSE
pamsbel-0.0.2.dist-info/METADATA
pamsbel-0.0.2.dist-info/WHEEL
pamsbel-0.0.2.dist-info/top_level.txt
pamsbel-0.0.2.dist-info/RECORD
