Metadata-Version: 2.1
Name: pamsbel
Version: 0.0.2
Summary: A module for the multiple signals predictive analysis
Author: Sergei Zuev
Author-email: shoukhov@mail.ru
Classifier: Programming Language :: Python :: 3.10
Classifier: Operating System :: OS Independent
Requires-Python: >=3.7
License-File: LICENSE
